<?xml version="1.0" encoding="utf-8" ?><dwsync><file name="index.php" server="Macintosh HD/Applications/MAMP/htdocs/minisitio_hh/" local="3523452074" remote="3523452074" Dst="-1" /><file name="index.php" server="Macintosh HD/Applications/MAMP/htdocs/cpiseguridad/" local="3548331825" remote="3548331825" Dst="-1" /><file name="index.php" server="Macintosh HD/Applications/MAMP/htdocs/CPI-Seguridad/" local="3549543376" remote="3549543376" Dst="-1" /><file name=".DS_Store" server="Macintosh HD/Applications/MAMP/htdocs/CPI-Seguridad/" local="3548781314" remote="3548781314" Dst="-1" /><file name="nosotros.php" server="Macintosh HD/Applications/MAMP/htdocs/CPI-Seguridad/" local="3549549219" remote="3549549219" Dst="-1" /><file name=".htaccess" server="Macintosh HD/Applications/MAMP/htdocs/CPI-Seguridad/" local="3549543376" remote="3549543376" Dst="-1" /><file name="reclutamiento.php" server="Macintosh HD/Applications/MAMP/htdocs/CPI-Seguridad/" local="3549543376" remote="3549543376" Dst="-1" /><file name=".gitignore" server="Macintosh HD/Applications/MAMP/htdocs/CPI-Seguridad/" local="3549543376" remote="3549543376" Dst="-1" /><file name=".DS_Store" server="ftp.upgrade.red" local="3548781314" remote="3550158900" Dst="-1" /><file name=".gitignore" server="ftp.upgrade.red" local="3549543376" remote="3550159140" Dst="-1" /><file name=".htaccess" server="ftp.upgrade.red" local="3549996314" remote="3550159140" Dst="-1" /><file name="nosotros.php" server="ftp.upgrade.red" local="3550848982" remote="3550852560" Dst="-1" /><file name="index.php" server="ftp.upgrade.red" local="3550756246" remote="3550759800" Dst="-1" /><file name="reclutamiento.php" server="ftp.upgrade.red" local="3549983740" remote="3550159140" Dst="-1" /><file name="prueba.html" server="ftp.upgrade.red" local="3549638158" remote="3550159140" Dst="-1" /><file name="contacto.php" server="ftp.upgrade.red" local="3551370659" remote="3551374260" Dst="-1" /></dwsync>